---
title: "2018-7-12日志"
date: "2018-07-12"
menu: "main"
---

## Git Bash命令别名配置  
配置git bash中别名：win+Q -> 查找Git Bash -> 右键打开文件位置 -> 找到Git Bash -> 右键打开文件位置 -> 找到文件：etc/bash.bashrc -> 使用编辑sublime或者vs code打开 -> 在末尾按照`alias dm='docker-machine'`格式进行配置

**在Git Bash 上连接远程Linux系统：**

```shell
ssh root@ip
```
# Docker学习

只有对比才有选择，Docker比其他类似产品有什么优越性？

## Docker基本概念

### Docker镜像——Image

Docker镜像（Image）是一个特殊的文件系统，由一组文件系统组成，包含了运行时所需的程序、库、资源、配置文件、配置参数等。镜像不包含任何动态数据，其内容在构建之后也不会发生改变。

#### 获取镜像

```shell
docker search mysql                    #搜索mysql的镜像
docker pull mysql                      #默认获取最新的mysql镜像,从Docker Hub获取镜像
```

### 运行

列出镜像

```shell
docker images                        #列出镜像
```
运行容器

```shell
docker run [OPTIONS] IMAGE [COMMAND] [ARG...]  #运行容器，docker run -d docker.io/mysql
```

### Docker容器——Container

容器是镜像运行的实体。容器可以被创建、启动、停止、删除、暂停等。

所有文件的写入都应该使用数据卷或者绑定宿主目录

### Docker仓库——Repository

一个仓库包含的是一个软件不同版本的对象。

## i++和++i的区别

**查看Java的字节码文件**

```java
javap -c Name.class
```

`int y = 5;int z = ++y + y++; // z=6+6` , 其字节码为：

```java
 0: iconst_5                //将int类型值5压入栈中                -->栈中元素：5
 1: istore_1                //弹出栈顶元素存入位置1的局部变量中    -->位置1元素：5
 2: iinc          1, 1      //将位置1的变量加1                   -->位置1元素：6
 5: iload_1                 //将位置1的元素压入栈                 -->栈中元素：6
 6: iload_1                 //将位置1的元素压入栈                 -->栈中元素：6，6
 7: iinc          1, 1      //将位置1中的元素加1                  -->位置1元素：7
 10: iadd                   //弹出栈顶2个元素相加，再压入栈        -->栈顶元素：12
 11: istore_2               //弹出栈顶元素存入位置2的局部变量      -->位置2元素：12
 12: return                 //最终结果：z=12，y=7
```

`int y = 5;int z = y++ + ++y; //z = 5 + 7;` , 其字节码：

```java
 0: iconst_5               //将int类型的值5压入栈中              -->栈顶元素：5
 1: istore_1               //弹出栈顶元素，存入位置1局部变量中    -->位置1元素：5
 2: iload_1                //将位置1的元素压入栈中               -->栈顶元素：5
 3: iinc          1, 1     //将位置1的元素加1                    -->位置1的元素：6
 6: iinc          1, 1     //将位置1的元素加1                    -->位置1的元素：7
 9: iload_1                //将位置1的元素压入栈顶               -->栈顶2个元素：7，5
10: iadd                   //弹出栈顶2个元素相加后再相加          -->栈顶元素：12                   
11: istore_2               //弹出栈顶元素并存入位置2局部变量        -->位置2的元素：12
12: return                 //最终结果：z=12，y = 7
```

**总结：**

- `++i;`和`i++;`单独作为一行算式并没有什么区别，因为没有进行赋值所以局部变量不会进行压栈操作
- 若是`j = i++`形式：先将i赋值给j，再进行加1运算；也就是先将i局部变量的是压入栈顶，局部变量i进行加1，然后将栈顶的元素弹出存入局部变量j
- 若是`j = ++1`形式：先进行加1运算，再将i赋值给j，即局部变量i加1，然后将局部变量i的值压入栈中，再将栈中的元素存入局部变量j
- 赋值运算是先将局部变量的值压入操作栈，再将操作栈顶弹出存入局部变量
- 运算符`++、--`比=的优先级高

### String比较

`String str = "hello";`是直接将常量从常量池压入栈顶，再将栈顶元素存入局部变量str对应的位置中。

`String str1 = new String("hello");`的字节码：

```java
 0: new           #2   // class java/lang/String;创建一个对象，并将其引用压入栈
 3: dup                //复制栈顶并将值压入栈顶
 4: ldc           #3  // String hello；将常量从常量池中压入栈顶
 6: invokespecial #4  // Method java/lang/String."<init>":(Ljava/lang/String;)V；调用超类的一些方法
 9: astore_1         //将栈顶元素存入局部变量str1对应的的位置
```
Java中使用`==`做比较，再JVM中使用的字节码是`if_acmpne`,是引用比较
